diamond/__init__.py
diamond/container/__init__.py
diamond/container/container.py
diamond/container/custom_image_builder/__init__.py
diamond/container/custom_image_builder/image_builder.py
diamond/container/custom_image_builder/exception/ImageBuilderException.py
diamond/container/custom_image_builder/exception/RegisterImageException.py
diamond/container/custom_image_builder/exception/__init__.py
diamond/diamond_client/__init__.py
diamond/diamond_client/diamond_client.py
diamond/diamond_client/templates/task_template
diamond/wrapper/__init__.py
diamond/wrapper/wrapper.py
example/__init__.py
example/run_online_image.py
example/openfold/__init__.py
example/openfold/multi_node_task.py
example/openfold/register_container.py
example/openfold/single_node_task.py
diamond_hpc-0.0.8.dist-info/LICENSE
diamond_hpc-0.0.8.dist-info/METADATA
diamond_hpc-0.0.8.dist-info/WHEEL
diamond_hpc-0.0.8.dist-info/entry_points.txt
diamond_hpc-0.0.8.dist-info/top_level.txt
diamond_hpc-0.0.8.dist-info/RECORD
