Metadata-Version: 2.1
Name: diamond-hpc
Version: 0.0.8
Summary: Diamond is a Python package for running tasks on HPC.
Home-page: https://github.com/Diamond-Proj/Diamond
Author: Haotian XIE, Gengcong YANG
Author-email: hotinexie@gmail.com
Classifier: Programming Language :: Python :: 3
Classifier: License :: OSI Approved :: MIT License
Classifier: Operating System :: OS Independent
Requires-Python: >=3.8
License-File: LICENSE
Requires-Dist: click >=8.1.3
Requires-Dist: globus-compute-sdk >=2.21.0
Requires-Dist: globus-sdk >=3.41.0
Requires-Dist: Jinja2 >=3.1.4
Requires-Dist: Requests >=2.32.2
Requires-Dist: setuptools >=59.6.0
